{
  "Financial Ratios": {
    "Market Capitalization": [
      {
        "2025-05-12": 561.0
      }
    ],
    "Market Cap Growth": [
      {
        "2025-05-12": -5.88
      }
    ],
    "Enterprise Value": [
      {
        "2025-05-12": 401.0
      }
    ],
    "Last Close Price": [
      {
        "2025-05-12": 3.34
      }
    ],
    "PE Ratio": [
      {
        "2025-05-12": 27.02
      }
    ],
    "PS Ratio": [
      {
        "2025-05-12": 1.77
      }
    ],
    "PB Ratio": [
      {
        "2025-05-12": 1.11
      }
    ],
    "P/TBV Ratio": [
      {
        "2025-05-12": 1.12
      }
    ],
    "P/FCF Ratio": [
      {
        "2025-05-12": 10.22
      }
    ],
    "P/OCF Ratio": [
      {
        "2025-05-12": 10.09
      }
    ],
    "EV/Sales Ratio": [
      {
        "2025-05-12": 1.26
      }
    ],
    "EV/EBITDA Ratio": [
      {
        "2025-05-12": 18.04
      }
    ],
    "EV/EBIT Ratio": [
      {
        "2025-05-12": 21.5
      }
    ],
    "EV/FCF Ratio": [
      {
        "2025-05-12": 7.3
      }
    ],
    "Debt / Equity Ratio": [
      {
        "2025-05-12": 0.02
      }
    ],
    "Debt / EBITDA Ratio": [
      {
        "2025-05-12": 0.2
      }
    ],
    "Debt / FCF Ratio": [
      {
        "2025-05-12": 0.16
      }
    ],
    "Asset Turnover": [
      {
        "2025-05-12": 0.52
      }
    ],
    "Quick Ratio": [
      {
        "2025-05-12": 3.83
      }
    ],
    "Current Ratio": [
      {
        "2025-05-12": 4.83
      }
    ],
    "Return on Equity (ROE)": [
      {
        "2025-05-12": 4.07
      }
    ],
    "Return on Assets (ROA)": [
      {
        "2025-05-12": 4.04
      }
    ],
    "Return on Capital (ROIC)": [
      {
        "2025-05-12": 4.64
      }
    ],
    "Return on Capital Employed (ROCE)": [
      {
        "2025-05-12": 7.6
      }
    ],
    "Earnings Yield": [
      {
        "2025-05-12": 3.52
      }
    ],
    "FCF Yield": [
      {
        "2025-05-12": 9.79
      }
    ],
    "Dividend Yield": [
      {
        "2025-05-12": 10.78
      }
    ],
    "Payout Ratio": [
      {
        "2025-05-12": 339.45
      }
    ],
    "Total Shareholder Return": [
      {
        "2025-05-12": 10.78
      }
    ]
  }
}