{
  "Balance Sheet": {
    "Cash & Equivalents": [
      {
        "2024-12-31": 517.74
      },
      {
        "2023-12-31": 665.42
      },
      {
        "2022-12-31": 289.29
      },
      {
        "2021-12-31": 114.96
      },
      {
        "2020-12-31": 193.01
      }
    ],
    "Cash & Short-Term Investments": [
      {
        "2024-12-31": 517.74
      },
      {
        "2023-12-31": 665.42
      },
      {
        "2022-12-31": 289.29
      },
      {
        "2021-12-31": 114.96
      },
      {
        "2020-12-31": 193.01
      }
    ],
    "Cash Growth": [
      {
        "2024-12-31": -22.19
      },
      {
        "2023-12-31": 130.02
      },
      {
        "2022-12-31": 151.64
      },
      {
        "2021-12-31": -40.44
      },
      {
        "2020-12-31": 879.28
      }
    ],
    "Other Receivables": [
      {
        "2024-12-31": 11.92
      },
      {
        "2023-12-31": 7.22
      },
      {
        "2022-12-31": 9.2
      },
      {
        "2021-12-31": 5.97
      },
      {
        "2020-12-31": 4.55
      }
    ],
    "Receivables": [
      {
        "2024-12-31": 11.92
      },
      {
        "2023-12-31": 23.58
      },
      {
        "2022-12-31": 13.68
      },
      {
        "2021-12-31": 5.97
      },
      {
        "2020-12-31": 4.55
      }
    ],
    "Inventory": [
      {
        "2024-12-31": 3259.0
      },
      {
        "2023-12-31": 2134.0
      },
      {
        "2022-12-31": 1464.0
      },
      {
        "2021-12-31": 473.96
      },
      {
        "2020-12-31": 1237.0
      }
    ],
    "Prepaid Expenses": [
      {
        "2024-12-31": 9.6
      },
      {
        "2023-12-31": 7.75
      },
      {
        "2022-12-31": 8.79
      },
      {
        "2021-12-31": 2.68
      },
      {
        "2020-12-31": 2.5
      }
    ],
    "Other Current Assets": [
      {
        "2024-12-31": 115.18
      },
      {
        "2023-12-31": 215.98
      },
      {
        "2022-12-31": 248.04
      },
      {
        "2021-12-31": 77.61
      },
      {
        "2020-12-31": 18.8
      }
    ],
    "Total Current Assets": [
      {
        "2024-12-31": 3913.0
      },
      {
        "2023-12-31": 3046.0
      },
      {
        "2022-12-31": 2024.0
      },
      {
        "2021-12-31": 675.18
      },
      {
        "2020-12-31": 1456.0
      }
    ],
    "Property, Plant & Equipment": [
      {
        "2024-12-31": 20.06
      },
      {
        "2023-12-31": 10.34
      },
      {
        "2022-12-31": 6.66
      },
      {
        "2021-12-31": 6.57
      },
      {
        "2020-12-31": 9.18
      }
    ],
    "Long-Term Investments": [
      {
        "2024-12-31": 216.76
      },
      {
        "2023-12-31": 350.25
      },
      {
        "2022-12-31": 212.88
      },
      {
        "2021-12-31": 211.34
      },
      {
        "2020-12-31": 216.94
      }
    ],
    "Other Intangible Assets": [
      {
        "2024-12-31": 0.13
      },
      {
        "2023-12-31": 0.16
      },
      {
        "2022-12-31": 0.16
      },
      {
        "2021-12-31": 0.13
      },
      {
        "2020-12-31": 1.92
      }
    ],
    "Long-Term Deferred Tax Assets": [
      {
        "2024-12-31": 46.52
      },
      {
        "2023-12-31": 13.71
      },
      {
        "2022-12-31": 42.87
      },
      {
        "2021-12-31": 3.43
      },
      {
        "2020-12-31": 1.59
      }
    ],
    "Other Long-Term Assets": [
      {
        "2024-12-31": 8.33
      },
      {
        "2023-12-31": 4.46
      },
      {
        "2022-12-31": 205.53
      },
      {
        "2021-12-31": 211.79
      },
      {
        "2020-12-31": 184.07
      }
    ],
    "Total Assets": [
      {
        "2024-12-31": 4205.0
      },
      {
        "2023-12-31": 3425.0
      },
      {
        "2022-12-31": 2492.0
      },
      {
        "2021-12-31": 1108.0
      },
      {
        "2020-12-31": 1870.0
      }
    ],
    "Accounts Payable": [
      {
        "2024-12-31": 63.46
      },
      {
        "2023-12-31": 109.73
      },
      {
        "2022-12-31": 27.52
      },
      {
        "2021-12-31": 15.12
      },
      {
        "2020-12-31": 32.32
      }
    ],
    "Accrued Expenses": [
      {
        "2024-12-31": 47.35
      },
      {
        "2023-12-31": 36.92
      },
      {
        "2022-12-31": 25.75
      },
      {
        "2021-12-31": 21.55
      },
      {
        "2020-12-31": 12.61
      }
    ],
    "Short-Term Debt": [
      {
        "2024-12-31": 298.52
      },
      {
        "2023-12-31": 4.65
      },
      {
        "2022-12-31": 261.67
      },
      {
        "2020-12-31": 40.0
      }
    ],
    "Current Portion of Long-Term Debt": [
      {
        "2024-12-31": 225.62
      },
      {
        "2023-12-31": 481.09
      },
      {
        "2020-12-31": 564.33
      }
    ],
    "Current Portion of Leases": [
      {
        "2024-12-31": 1.57
      },
      {
        "2023-12-31": 0.77
      },
      {
        "2022-12-31": 1.86
      },
      {
        "2021-12-31": 1.42
      },
      {
        "2020-12-31": 1.39
      }
    ],
    "Current Income Taxes Payable": [
      {
        "2024-12-31": 61.25
      },
      {
        "2023-12-31": 52.97
      },
      {
        "2022-12-31": 15.5
      },
      {
        "2021-12-31": 26.63
      },
      {
        "2020-12-31": 2.46
      }
    ],
    "Current Unearned Revenue": [
      {
        "2024-12-31": 11.96
      },
      {
        "2023-12-31": 10.63
      },
      {
        "2022-12-31": 9.89
      },
      {
        "2021-12-31": 12.35
      },
      {
        "2020-12-31": 175.73
      }
    ],
    "Other Current Liabilities": [
      {
        "2024-12-31": 142.35
      },
      {
        "2023-12-31": 405.77
      },
      {
        "2022-12-31": 221.69
      },
      {
        "2021-12-31": 49.81
      },
      {
        "2020-12-31": 143.59
      }
    ],
    "Total Current Liabilities": [
      {
        "2024-12-31": 852.07
      },
      {
        "2023-12-31": 1103.0
      },
      {
        "2022-12-31": 563.88
      },
      {
        "2021-12-31": 126.88
      },
      {
        "2020-12-31": 972.44
      }
    ],
    "Long-Term Debt": [
      {
        "2024-12-31": 1647.0
      },
      {
        "2023-12-31": 918.44
      },
      {
        "2022-12-31": 1030.0
      },
      {
        "2021-12-31": 151.69
      },
      {
        "2020-12-31": 199.92
      }
    ],
    "Long-Term Leases": [
      {
        "2024-12-31": 5.44
      },
      {
        "2023-12-31": 0.4
      },
      {
        "2022-12-31": 0.48
      },
      {
        "2021-12-31": 1.33
      },
      {
        "2020-12-31": 2.58
      }
    ],
    "Long-Term Deferred Tax Liabilities": [
      {
        "2024-12-31": 0.31
      },
      {
        "2023-12-31": 0.21
      },
      {
        "2022-12-31": 0.21
      },
      {
        "2021-12-31": 0.25
      },
      {
        "2020-12-31": 1.66
      }
    ],
    "Other Long-Term Liabilities": [
      {
        "2024-12-31": 1.51
      }
    ],
    "Total Liabilities": [
      {
        "2024-12-31": 2508.0
      },
      {
        "2023-12-31": 2023.0
      },
      {
        "2022-12-31": 1596.0
      },
      {
        "2021-12-31": 281.44
      },
      {
        "2020-12-31": 1179.0
      }
    ],
    "Common Stock": [
      {
        "2024-12-31": 604.69
      },
      {
        "2023-12-31": 604.69
      },
      {
        "2022-12-31": 604.69
      },
      {
        "2021-12-31": 604.69
      },
      {
        "2020-12-31": 604.69
      }
    ],
    "Additional Paid-In Capital": [
      {
        "2024-12-31": 3.42
      },
      {
        "2023-12-31": 3.41
      },
      {
        "2022-12-31": 3.41
      },
      {
        "2021-12-31": 3.41
      },
      {
        "2020-12-31": 18.82
      }
    ],
    "Retained Earnings": [
      {
        "2024-12-31": 949.39
      },
      {
        "2023-12-31": 555.9
      },
      {
        "2022-12-31": 49.47
      },
      {
        "2021-12-31": -36.52
      },
      {
        "2020-12-31": -168.08
      }
    ],
    "Treasury Stock": [
      {
        "2024-12-31": -98.11
      }
    ],
    "Comprehensive Income & Other": [
      {
        "2024-12-31": 237.81
      },
      {
        "2023-12-31": 237.81
      },
      {
        "2022-12-31": 237.81
      },
      {
        "2021-12-31": 238.04
      },
      {
        "2020-12-31": 222.64
      }
    ],
    "Total Common Equity": [
      {
        "2024-12-31": 1697.0
      },
      {
        "2023-12-31": 1402.0
      },
      {
        "2022-12-31": 895.38
      },
      {
        "2021-12-31": 809.63
      },
      {
        "2020-12-31": 678.07
      }
    ],
    "Shareholders' Equity": [
      {
        "2024-12-31": 1697.0
      },
      {
        "2023-12-31": 1402.0
      },
      {
        "2022-12-31": 895.38
      },
      {
        "2021-12-31": 827.0
      },
      {
        "2020-12-31": 691.23
      }
    ],
    "Total Liabilities & Equity": [
      {
        "2024-12-31": 4205.0
      },
      {
        "2023-12-31": 3425.0
      },
      {
        "2022-12-31": 2492.0
      },
      {
        "2021-12-31": 1108.0
      },
      {
        "2020-12-31": 1870.0
      }
    ],
    "Total Debt": [
      {
        "2024-12-31": 2178.0
      },
      {
        "2023-12-31": 1405.0
      },
      {
        "2022-12-31": 1294.0
      },
      {
        "2021-12-31": 154.44
      },
      {
        "2020-12-31": 808.23
      }
    ],
    "Net Cash (Debt)": [
      {
        "2024-12-31": -1660.0
      },
      {
        "2023-12-31": -739.93
      },
      {
        "2022-12-31": -1005.0
      },
      {
        "2021-12-31": -39.48
      },
      {
        "2020-12-31": -615.22
      }
    ],
    "Net Cash Per Share": [
      {
        "2024-12-31": -1.39
      },
      {
        "2023-12-31": -0.61
      },
      {
        "2022-12-31": -0.83
      },
      {
        "2021-12-31": -0.03
      },
      {
        "2020-12-31": -0.52
      }
    ],
    "Filing Date Shares Outstanding": [
      {
        "2024-12-31": 1178.0
      },
      {
        "2023-12-31": 1209.0
      },
      {
        "2022-12-31": 1209.0
      },
      {
        "2021-12-31": 1209.0
      },
      {
        "2020-12-31": 1209.0
      }
    ],
    "Total Common Shares Outstanding": [
      {
        "2024-12-31": 1178.0
      },
      {
        "2023-12-31": 1209.0
      },
      {
        "2022-12-31": 1209.0
      },
      {
        "2021-12-31": 1209.0
      },
      {
        "2020-12-31": 1209.0
      }
    ],
    "Working Capital": [
      {
        "2024-12-31": 3061.0
      },
      {
        "2023-12-31": 1944.0
      },
      {
        "2022-12-31": 1460.0
      },
      {
        "2021-12-31": 548.3
      },
      {
        "2020-12-31": 483.67
      }
    ],
    "Book Value Per Share": [
      {
        "2024-12-31": 1.44
      },
      {
        "2023-12-31": 1.16
      },
      {
        "2022-12-31": 0.74
      },
      {
        "2021-12-31": 0.67
      },
      {
        "2020-12-31": 0.56
      }
    ],
    "Tangible Book Value": [
      {
        "2024-12-31": 1697.0
      },
      {
        "2023-12-31": 1402.0
      },
      {
        "2022-12-31": 895.22
      },
      {
        "2021-12-31": 809.51
      },
      {
        "2020-12-31": 676.15
      }
    ],
    "Tangible Book Value Per Share": [
      {
        "2024-12-31": 1.44
      },
      {
        "2023-12-31": 1.16
      },
      {
        "2022-12-31": 0.74
      },
      {
        "2021-12-31": 0.67
      },
      {
        "2020-12-31": 0.56
      }
    ],
    "Land": [
      {
        "2024-12-31": 2.6
      },
      {
        "2023-12-31": 2.6
      }
    ],
    "Buildings": [
      {
        "2024-12-31": 6.98
      },
      {
        "2023-12-31": 2.95
      },
      {
        "2022-12-31": 2.29
      },
      {
        "2021-12-31": 2.22
      },
      {
        "2020-12-31": 2.56
      }
    ],
    "Machinery": [
      {
        "2024-12-31": 18.65
      },
      {
        "2023-12-31": 16.37
      },
      {
        "2022-12-31": 14.02
      },
      {
        "2021-12-31": 11.97
      },
      {
        "2020-12-31": 9.48
      }
    ],
    "Construction In Progress": [
      {
        "2023-12-31": 0.23
      }
    ],
    "Minority Interest": [
      {
        "2021-12-31": 17.37
      },
      {
        "2020-12-31": 13.16
      }
    ]
  }
}